numba_kdtree/__init__.py
numba_kdtree/_ckdtree.lib
numba_kdtree/_version.py
numba_kdtree/ckdtree.py
numba_kdtree/kd_tree.py
numba_kdtree-0.6.0.dist-info/METADATA
numba_kdtree-0.6.0.dist-info/WHEEL
numba_kdtree-0.6.0.dist-info/top_level.txt
numba_kdtree-0.6.0.dist-info/zip-safe
numba_kdtree-0.6.0.dist-info/RECORD
