Metadata-Version: 2.2
Name: numba-kdtree
Version: 0.6.0
Summary: A kdtree implementation for numba.
Author-email: Felix Igelbrink <felix.igelbrink@dfki.de>
License: MIT
Project-URL: Homepage, https://github.com/mortacious/numba-kdtree
Project-URL: Issues, https://github.com/mortacious/numba-kdtree/issues
Classifier: Programming Language :: Python :: 3.9
Classifier: Programming Language :: Python :: 3.10
Classifier: Programming Language :: Python :: 3.11
Classifier: Programming Language :: Python :: 3.12
Classifier: Programming Language :: Python :: 3.13
Classifier: License :: OSI Approved :: MIT License
Classifier: Operating System :: POSIX :: Linux
Classifier: Operating System :: Microsoft :: Windows
Classifier: Intended Audience :: Developers
Classifier: Intended Audience :: Science/Research
Classifier: Topic :: Scientific/Engineering
Classifier: Topic :: Software Development
Requires-Python: >=3.9
Requires-Dist: numba>=0.52
Provides-Extra: test
Requires-Dist: pytest; extra == "test"
Requires-Dist: scipy; extra == "test"
Requires-Dist: requests; extra == "test"
Requires-Dist: plyfile; extra == "test"
